<?xml version="1.0" encoding="utf-8"?>
<TAUNTS>
  <TAUNT>
    <uiIndex>0</uiIndex>
    <szText>What the hell am I going to do now?</szText>
  </TAUNT>
  <TAUNT>
    <uiIndex>1</uiIndex>
    <szText>I'm all out!</szText>
  </TAUNT>
  <TAUNT>
    <uiIndex>2</uiIndex>
    <szText>I'm running dry over here!</szText>
  </TAUNT>
  <TAUNT>
    <uiIndex>3</uiIndex>
    <szText>Need more ammo!</szText>
  </TAUNT>
  <TAUNT>
    <uiIndex>4</uiIndex>
    <szText>I'm out of bullets!</szText>
  </TAUNT>
  <TAUNT>
    <uiIndex>5</uiIndex>
    <szText>Need supplies!</szText>
  </TAUNT>
</TAUNTS>
