<?xml version="1.0" encoding="utf-8"?>
<TAUNTS>
  <TAUNT>
    <uiIndex>0</uiIndex>
    <szText>"Эй, кто меня тронул?</szText>
  </TAUNT>
  <TAUNT>
    <uiIndex>1</uiIndex>
    <szText>Эй, разве мама не покупала тебе собственные игрушки?</szText>
  </TAUNT>
  <TAUNT>
    <uiIndex>2</uiIndex>
    <szText>Черт, а ты шустрый!</szText>
  </TAUNT>
  <TAUNT>
    <uiIndex>3</uiIndex>
    <szText>Ворованное барахло приведёт тебя в могилу!</szText>
  </TAUNT>
  <TAUNT>
    <uiIndex>4</uiIndex>
    <szText>Эй! Это моё!</szText>
  </TAUNT>
  <TAUNT>
    <uiIndex>5</uiIndex>
    <szText>Сам себе заработай на вещи, нищеброд!</szText>
  </TAUNT>
  <TAUNT>
    <uiIndex>6</uiIndex>
    <szText>Ха... Можешь оставить это себе - всё равно это хлам!</szText>
  </TAUNT>
  <TAUNT>
    <uiIndex>7</uiIndex>
    <szText>Я тебе руки оторву за это, ублюдок!</szText>
  </TAUNT>
  <TAUNT>
    <uiIndex>8</uiIndex>
    <szText>Я покажу тебе, что мы делаем с ворами в наших краях!</szText>
  </TAUNT>
</TAUNTS>
